watools/Collect_Tools.py
watools/WebAccounts.py
watools/__init__.py
watools/Collect/__init__.py
watools/Collect/ALEXI/DataAccess.py
watools/Collect/ALEXI/__init__.py
watools/Collect/ALEXI/daily.py
watools/Collect/ALEXI/monthly.py
watools/Collect/ALEXI/weekly.py
watools/Collect/ASCAT/DataAccess.py
watools/Collect/ASCAT/__init__.py
watools/Collect/ASCAT/daily.py
watools/Collect/CFSR/DataAccess_CFSR.py
watools/Collect/CFSR/Download_data_CFSR.py
watools/Collect/CFSR/__init__.py
watools/Collect/CFSR/daily.py
watools/Collect/CHIRPS/DataAccess.py
watools/Collect/CHIRPS/__init__.py
watools/Collect/CHIRPS/daily.py
watools/Collect/CHIRPS/monthly.py
watools/Collect/CMRSET/DataAccess.py
watools/Collect/CMRSET/__init__.py
watools/Collect/CMRSET/monthly.py
watools/Collect/DEM/DataAccess.py
watools/Collect/DEM/HydroSHED.py
watools/Collect/DEM/HydroSHED_Dir.py
watools/Collect/DEM/__init__.py
watools/Collect/ECMWF/DataAccess.py
watools/Collect/ECMWF/ECMWFdownload.py
watools/Collect/ECMWF/__init__.py
watools/Collect/ECMWF/daily.py
watools/Collect/ECMWF/monthly.py
watools/Collect/ETmonitor/DataAccess.py
watools/Collect/ETmonitor/ET_monthly.py
watools/Collect/ETmonitor/ETpot_monthly.py
watools/Collect/ETmonitor/Ei_monthly.py
watools/Collect/ETmonitor/Es_monthly.py
watools/Collect/ETmonitor/Ew_monthly.py
watools/Collect/ETmonitor/Tr_monthly.py
watools/Collect/ETmonitor/__init__.py
watools/Collect/FEWS/ETpot_daily.py
watools/Collect/FEWS/__init__.py
watools/Collect/GLDAS/CLSM_DataAccess.py
watools/Collect/GLDAS/CLSM_daily.py
watools/Collect/GLDAS/CLSM_monthly.py
watools/Collect/GLDAS/CLSM_three_hourly.py
watools/Collect/GLDAS/DataAccess.py
watools/Collect/GLDAS/NOAH_DataAccess.py
watools/Collect/GLDAS/NOAH_daily.py
watools/Collect/GLDAS/NOAH_monthly.py
watools/Collect/GLDAS/NOAH_three_hourly.py
watools/Collect/GLDAS/__init__.py
watools/Collect/GLDAS/daily.py
watools/Collect/GLDAS/monthly.py
watools/Collect/GLDAS/three_hourly.py
watools/Collect/GLEAM/DataAccess.py
watools-0.0.8.dist-info/LICENSE
watools-0.0.8.dist-info/METADATA
watools-0.0.8.dist-info/WHEEL
watools-0.0.8.dist-info/top_level.txt
watools-0.0.8.dist-info/RECORD
